ptwrapper/.flake8
ptwrapper/__init__.py
ptwrapper/cli.py
ptwrapper/config/agm/cfg_agm_jui.xml
ptwrapper/config/agm/cfg_agm_jui_event_definitions.xml
ptwrapper/config/agm/cfg_agm_jui_fixed_definitions.xml
ptwrapper/config/agm/cfg_agm_jui_predefined_block.xml
ptwrapper/config/eps/BRF_MAL_SGICD_2_1_300101_351005.brf
ptwrapper/config/eps/RES_C50_SA_CELLS_EFFICIENCY_310101_351003.csv
ptwrapper/config/eps/eps.cfg
ptwrapper/config/eps/events.juice.def
ptwrapper/config/eps/phs_com_res_sa_cells_count.asc
ptwrapper/config/eps/units.def
ptwrapper/config/session_file.json
ptwrapper/html_log.py
ptwrapper/input/TOP__events.evf
ptwrapper/input/TOP_crema_5_0_events.evf
ptwrapper/input/TOP_crema_5_1_150lb_23_1_a3_events.evf
ptwrapper/input/TOP_crema_5_1_150lb_23_1_events.evf
ptwrapper/input/downlink.evf
ptwrapper/input/edf/EDF_JUI_SPC_LINK_KAB.edf
ptwrapper/input/edf/EDF_JUI_SPC_LINK_XB.edf
ptwrapper/input/edf/TBD.edf
ptwrapper/input/edf/TOP_experiments.edf
ptwrapper/input/edf/juice__spacecraft.edf
ptwrapper/input/edf/juice__spacecraft_platform.edf
ptwrapper/input/edf/juice__spacecraft_ssmm.edf
ptwrapper/input/evf/EVT_CREMA_5_0_GEOPIPELINE.EVF
ptwrapper/input/evf/EVT_CREMA_5_1_150LB_23_1_A3_GEOPIPELINE.EVF
ptwrapper/input/evf/EVT_CREMA_5_1_150LB_23_1_GEOPIPELINE.EVF
ptwrapper/input/evf/EVT__GEOPIPELINE.EVF
ptwrapper/input/itl/TBD.itl
ptwrapper/input/itl/TOP_timelines.itl
ptwrapper/input/itl/downlink.itl
ptwrapper/input/itl/platform.itl
ptwrapper/main.py
ptwrapper/py.typed
ptwrapper/subscribers.py
ptwrapper/utils.py
ptwrapper-2.7.2.dist-info/METADATA
ptwrapper-2.7.2.dist-info/WHEEL
ptwrapper-2.7.2.dist-info/entry_points.txt
ptwrapper-2.7.2.dist-info/licenses/LICENSE.txt
ptwrapper-2.7.2.dist-info/RECORD
