Metadata-Version: 2.4
Name: ptwrapper
Version: 2.7.2
Summary: A Pointing Tool OSVE wrapper
License: European Space Agency Public License (ESA-PL) Permissive (Type 3) – v2.4
License-File: LICENSE.txt
Author: Marc Costa
Author-email: marc.costa@ext.esa.int
Requires-Python: >=3.8,<4.0
Classifier: Development Status :: 4 - Beta
Classifier: Intended Audience :: Developers
Classifier: License :: Other/Proprietary License
Classifier: Operating System :: OS Independent
Classifier: Programming Language :: Python
Classifier: Programming Language :: Python :: 3
Classifier: Programming Language :: Python :: 3.8
Classifier: Programming Language :: Python :: 3.9
Classifier: Programming Language :: Python :: 3.10
Classifier: Programming Language :: Python :: 3.11
Classifier: Programming Language :: Python :: 3.12
Classifier: Programming Language :: Python :: 3.13
Classifier: Programming Language :: Python :: 3.14
Classifier: Topic :: Software Development :: Libraries :: Python Modules
Classifier: Typing :: Typed
Requires-Dist: numpy (>=1.26.4)
Requires-Dist: osve (==2.7.2)
Requires-Dist: spiceypy (>=5.1.2)
Project-URL: Documentation, https://juicesoc.esac.esa.int/panel/#/navigation/help
Project-URL: Homepage, https://gitlab.esa.int/juice-soc-public/python/ptwrapper
Project-URL: Repository, https://gitlab.esa.int/juice-soc-public/python/ptwrapper
